[{"system.totimestamp(timeuuid)":"2021-05-20T14:31:46.428Z","rssi":-83,"distance":6.309573444801933,"channel":38},{"system.totimestamp(timeuuid)":"2021-05-20T14:31:45.920Z","rssi":-81,"distance":6.165950018614819,"channel":38},{"system.totimestamp(timeuuid)":"2021-05-20T14:31:45.415Z","rssi":-82,"distance":6.309573444801933,"channel":38},{"system.totimestamp(timeuuid)":"2021-05-20T14:31:44.910Z","rssi":-82,"distance":6.025595860743573,"channel":38},{"system.totimestamp(timeuuid)":"2021-05-20T14:31:44.404Z","rssi":-82,"distance":5.754399373371571,"channel":38},{"system.totimestamp(timeuuid)":"2021-05-20T14:31:39.829Z","rssi":-82,"distance":5.495408738576244,"channel":37},{"system.totimestamp(timeuuid)":"2021-05-20T14:31:39.322Z","rssi":-82,"distance":5.370317963702524,"channel":37},{"system.totimestamp(timeuuid)":"2021-05-20T14:31:38.816Z","rssi":-80,"distance":5.24807460249773,"channel":37},{"system.totimestamp(timeuuid)":"2021-05-20T14:31:38.310Z","rssi":-80,"distance":5.24807460249773,"channel":39},{"system.totimestamp(timeuuid)":"2021-05-20T14:31:37.805Z","rssi":-80,"distance":5.370317963702524,"channel":39},{"system.totimestamp(timeuuid)":"2021-05-20T14:31:37.299Z","rssi":-81,"distance":5.623413251903491,"channel":39},{"system.totimestamp(timeuuid)":"2021-05-20T14:31:36.794Z","rssi":-81,"distance":5.754399373371571,"channel":39},{"system.totimestamp(timeuuid)":"2021-05-20T14:31:36.289Z","rssi":-80,"distance":5.888436553555893,"channel":39},{"system.totimestamp(timeuuid)":"2021-05-20T14:31:35.783Z","rssi":-81,"distance":6.165950018614819,"channel":39},{"system.totimestamp(timeuuid)":"2021-05-20T14:31:35.276Z","rssi":-82,"distance":6.309573444801933,"channel":39},{"system.totimestamp(timeuuid)":"2021-05-20T14:31:34.771Z","rssi":-82,"distance":6.309573444801933,"channel":39},{"system.totimestamp(timeuuid)":"2021-05-20T14:31:34.265Z","rssi":-82,"distance":6.456542290346557,"channel":38},{"system.totimestamp(timeuuid)":"2021-05-20T14:31:33.760Z","rssi":-82,"distance":6.606934480075965,"channel":38},{"system.totimestamp(timeuuid)":"2021-05-20T14:31:33.254Z","rssi":-82,"distance":6.606934480075965,"channel":38},{"system.totimestamp(timeuuid)":"2021-05-20T14:31:32.746Z","rssi":-82,"distance":6.309573444801933,"channel":38},{"system.totimestamp(timeuuid)":"2021-05-20T14:31:32.239Z","rssi":-83,"distance":6.025595860743573,"channel":38},{"system.totimestamp(timeuuid)":"2021-05-20T14:31:31.734Z","rssi":-83,"distance":5.623413251903491,"channel":38},{"system.totimestamp(timeuuid)":"2021-05-20T14:31:31.227Z","rssi":-82,"distance":5.24807460249773,"channel":38},{"system.totimestamp(timeuuid)":"2021-05-20T14:31:30.720Z","rssi":-80,"distance":5.011872336272722,"channel":38},{"system.totimestamp(timeuuid)":"2021-05-20T14:31:30.214Z","rssi":-80,"distance":5.495408738576244,"channel":37},{"system.totimestamp(timeuuid)":"2021-05-20T14:31:29.708Z","rssi":-80,"distance":5.754399373371571,"channel":37},{"system.totimestamp(timeuuid)":"2021-05-20T14:31:29.203Z","rssi":-80,"distance":6.025595860743573,"channel":37},{"system.totimestamp(timeuuid)":"2021-05-20T14:31:28.699Z","rssi":-80,"distance":6.025595860743573,"channel":37},{"system.totimestamp(timeuuid)":"2021-05-20T14:31:28.196Z","rssi":-84,"distance":6.025595860743573,"channel":37},{"system.totimestamp(timeuuid)":"2021-05-20T14:31:27.690Z","rssi":-82,"distance":5.495408738576244,"channel":37},{"system.totimestamp(timeuuid)":"2021-05-20T14:31:27.186Z","rssi":-82,"distance":5.24807460249773,"channel":37},{"system.totimestamp(timeuuid)":"2021-05-20T14:31:26.681Z","rssi":-80,"distance":5.128613839913651,"channel":37},{"system.totimestamp(timeuuid)":"2021-05-20T14:31:26.177Z","rssi":-80,"distance":5.128613839913651,"channel":39},{"system.totimestamp(timeuuid)":"2021-05-20T14:31:25.672Z","rssi":-80,"distance":5.128613839913651,"channel":39},{"system.totimestamp(timeuuid)":"2021-05-20T14:31:25.167Z","rssi":-80,"distance":5.128613839913651,"channel":39},{"system.totimestamp(timeuuid)":"2021-05-20T14:31:24.663Z","rssi":-81,"distance":5.128613839913651,"channel":39},{"system.totimestamp(timeuuid)":"2021-05-20T14:31:24.157Z","rssi":-80,"distance":5.011872336272722,"channel":39},{"system.totimestamp(timeuuid)":"2021-05-20T14:31:23.653Z","rssi":-80,"distance":5.128613839913651,"channel":39},{"system.totimestamp(timeuuid)":"2021-05-20T14:31:23.148Z","rssi":-80,"distance":5.24807460249773,"channel":39},{"system.totimestamp(timeuuid)":"2021-05-20T14:31:19.087Z","rssi":-80,"distance":5.495408738576244,"channel":38},{"system.totimestamp(timeuuid)":"2021-05-20T14:31:18.581Z","rssi":-80,"distance":5.754399373371571,"channel":38},{"system.totimestamp(timeuuid)":"2021-05-20T14:31:18.077Z","rssi":-81,"distance":5.888436553555893,"channel":38},{"system.totimestamp(timeuuid)":"2021-05-20T14:31:17.571Z","rssi":-81,"distance":5.754399373371571,"channel":37},{"system.totimestamp(timeuuid)":"2021-05-20T14:31:17.066Z","rssi":-82,"distance":5.623413251903491,"channel":37},{"system.totimestamp(timeuuid)":"2021-05-20T14:31:16.561Z","rssi":-82,"distance":5.623413251903491,"channel":37},{"system.totimestamp(timeuuid)":"2021-05-20T14:31:16.056Z","rssi":-81,"distance":5.623413251903491,"channel":37},{"system.totimestamp(timeuuid)":"2021-05-20T14:31:15.551Z","rssi":-80,"distance":5.623413251903491,"channel":37},{"system.totimestamp(timeuuid)":"2021-05-20T14:31:15.046Z","rssi":-80,"distance":5.754399373371571,"channel":37},{"system.totimestamp(timeuuid)":"2021-05-20T14:31:14.541Z","rssi":-82,"distance":5.754399373371571,"channel":37},{"system.totimestamp(timeuuid)":"2021-05-20T14:31:14.036Z","rssi":-82,"distance":5.495408738576244,"channel":37},{"system.totimestamp(timeuuid)":"2021-05-20T14:31:13.531Z","rssi":-81,"distance":5.24807460249773,"channel":39},{"system.totimestamp(timeuuid)":"2021-05-20T14:31:13.026Z","rssi":-81,"distance":5.24807460249773,"channel":39},{"system.totimestamp(timeuuid)":"2021-05-20T14:31:12.522Z","rssi":-80,"distance":5.623413251903491,"channel":39},{"system.totimestamp(timeuuid)":"2021-05-20T14:31:12.016Z","rssi":-80,"distance":6.309573444801933,"channel":39},{"system.totimestamp(timeuuid)":"2021-05-20T14:31:11.511Z","rssi":-80,"distance":6.918309709189363,"channel":39},{"system.totimestamp(timeuuid)":"2021-05-20T14:31:11.001Z","rssi":-81,"distance":7.585775750291832,"channel":39},{"system.totimestamp(timeuuid)":"2021-05-20T14:31:10.496Z","rssi":-84,"distance":8.51138038202376,"channel":39},{"system.totimestamp(timeuuid)":"2021-05-20T14:31:09.992Z","rssi":-85,"distance":9.120108393559102,"channel":39},{"system.totimestamp(timeuuid)":"2021-05-20T14:31:09.483Z","rssi":-84,"distance":9.332543007969917,"channel":38},{"system.totimestamp(timeuuid)":"2021-05-20T14:31:08.978Z","rssi":-84,"distance":9.120108393559102,"channel":38},{"system.totimestamp(timeuuid)":"2021-05-20T14:31:08.474Z","rssi":-86,"distance":8.709635899560803,"channel":38},{"system.totimestamp(timeuuid)":"2021-05-20T14:31:07.968Z","rssi":-87,"distance":7.943282347242816,"channel":38},{"system.totimestamp(timeuuid)":"2021-05-20T14:31:06.954Z","rssi":-86,"distance":6.760829753919814,"channel":38},{"system.totimestamp(timeuuid)":"2021-05-20T14:31:06.450Z","rssi":-83,"distance":5.888436553555893,"channel":38},{"system.totimestamp(timeuuid)":"2021-05-20T14:31:05.944Z","rssi":-82,"distance":5.495408738576244,"channel":38},{"system.totimestamp(timeuuid)":"2021-05-20T14:31:05.439Z","rssi":-82,"distance":5.24807460249773,"channel":37},{"system.totimestamp(timeuuid)":"2021-05-20T14:31:04.422Z","rssi":-80,"distance":5.495408738576244,"channel":37},{"system.totimestamp(timeuuid)":"2021-05-20T14:31:03.915Z","rssi":-80,"distance":6.025595860743573,"channel":37},{"system.totimestamp(timeuuid)":"2021-05-20T14:31:03.409Z","rssi":-80,"distance":6.456542290346557,"channel":37},{"system.totimestamp(timeuuid)":"2021-05-20T14:31:02.904Z","rssi":-80,"distance":7.079457843841379,"channel":37},{"system.totimestamp(timeuuid)":"2021-05-20T14:30:58.844Z","rssi":-84,"distance":7.943282347242816,"channel":39},{"system.totimestamp(timeuuid)":"2021-05-20T14:30:58.334Z","rssi":-84,"distance":8.128305161640995,"channel":39},{"system.totimestamp(timeuuid)":"2021-05-20T14:30:57.829Z","rssi":-83,"distance":8.128305161640995,"channel":39},{"system.totimestamp(timeuuid)":"2021-05-20T14:30:57.323Z","rssi":-84,"distance":8.128305161640995,"channel":38},{"system.totimestamp(timeuuid)":"2021-05-20T14:30:56.815Z","rssi":-85,"distance":8.709635899560803,"channel":38},{"system.totimestamp(timeuuid)":"2021-05-20T14:30:56.309Z","rssi":-85,"distance":8.128305161640995,"channel":38},{"system.totimestamp(timeuuid)":"2021-05-20T14:30:55.805Z","rssi":-84,"distance":7.2443596007499025,"channel":38},{"system.totimestamp(timeuuid)":"2021-05-20T14:30:55.301Z","rssi":-83,"distance":6.606934480075965,"channel":38},{"system.totimestamp(timeuuid)":"2021-05-20T14:30:54.792Z","rssi":-87,"distance":6.309573444801933,"channel":38},{"system.totimestamp(timeuuid)":"2021-05-20T14:30:54.287Z","rssi":-82,"distance":5.623413251903491,"channel":38},{"system.totimestamp(timeuuid)":"2021-05-20T14:30:53.781Z","rssi":-80,"distance":5.370317963702524,"channel":38},{"system.totimestamp(timeuuid)":"2021-05-20T14:30:53.276Z","rssi":-80,"distance":5.370317963702524,"channel":37},{"system.totimestamp(timeuuid)":"2021-05-20T14:30:52.772Z","rssi":-81,"distance":5.623413251903491,"channel":37},{"system.totimestamp(timeuuid)":"2021-05-20T14:30:52.266Z","rssi":-82,"distance":6.165950018614819,"channel":37},{"system.totimestamp(timeuuid)":"2021-05-20T14:30:51.758Z","rssi":-80,"distance":7.079457843841379,"channel":37},{"system.totimestamp(timeuuid)":"2021-05-20T14:30:51.253Z","rssi":-80,"distance":8.51138038202376,"channel":37},{"system.totimestamp(timeuuid)":"2021-05-20T14:30:50.749Z","rssi":-82,"distance":9.772372209558105,"channel":37},{"system.totimestamp(timeuuid)":"2021-05-20T14:30:50.243Z","rssi":-85,"distance":10.471285480509001,"channel":37},{"system.totimestamp(timeuuid)":"2021-05-20T14:30:49.737Z","rssi":-88,"distance":10,"channel":37},{"system.totimestamp(timeuuid)":"2021-05-20T14:30:49.233Z","rssi":-88,"distance":9.772372209558105,"channel":39},{"system.totimestamp(timeuuid)":"2021-05-20T14:30:48.728Z","rssi":-86,"distance":9.120108393559102,"channel":39},{"system.totimestamp(timeuuid)":"2021-05-20T14:30:48.223Z","rssi":-85,"distance":9.332543007969917,"channel":39},{"system.totimestamp(timeuuid)":"2021-05-20T14:30:47.718Z","rssi":-83,"distance":9.772372209558105,"channel":39},{"system.totimestamp(timeuuid)":"2021-05-20T14:30:47.213Z","rssi":-87,"distance":10.471285480509001,"channel":39},{"system.totimestamp(timeuuid)":"2021-05-20T14:30:46.708Z","rssi":-85,"distance":9.549925860214355,"channel":39},{"system.totimestamp(timeuuid)":"2021-05-20T14:30:46.202Z","rssi":-87,"distance":8.709635899560803,"channel":39},{"system.totimestamp(timeuuid)":"2021-05-20T14:30:45.698Z","rssi":-87,"distance":8.128305161640995,"channel":39},{"system.totimestamp(timeuuid)":"2021-05-20T14:30:45.193Z","rssi":-86,"distance":7.413102413009181,"channel":38},{"system.totimestamp(timeuuid)":"2021-05-20T14:30:44.688Z","rssi":-83,"distance":6.606934480075965,"channel":38},{"system.totimestamp(timeuuid)":"2021-05-20T14:30:44.182Z","rssi":-81,"distance":6.165950018614819,"channel":38}]