[{"beacon_address":"20:18:FF:00:40:2D","system.totimestamp(timeuuid)":"2021-06-06T14:28:31.139Z","rssi":-89,"distance":2.570395782768865,"channel":37},{"beacon_address":"20:18:FF:00:40:2D","system.totimestamp(timeuuid)":"2021-06-06T14:28:30.627Z","rssi":-76,"distance":1.6982436524617432,"channel":37},{"beacon_address":"20:18:FF:00:40:2D","system.totimestamp(timeuuid)":"2021-06-06T14:28:29.607Z","rssi":-70,"distance":1.1748975549395304,"channel":37},{"beacon_address":"20:18:FF:00:40:2D","system.totimestamp(timeuuid)":"2021-06-06T14:28:29.085Z","rssi":-79,"distance":1.1748975549395304,"channel":37},{"beacon_address":"20:18:FF:00:40:2D","system.totimestamp(timeuuid)":"2021-06-06T14:28:28.570Z","rssi":-67,"distance":0.8128305161640995,"channel":39},{"beacon_address":"20:18:FF:00:40:2D","system.totimestamp(timeuuid)":"2021-06-06T14:28:28.067Z","rssi":-71,"distance":0.8511380382023759,"channel":39},{"beacon_address":"20:18:FF:00:40:2D","system.totimestamp(timeuuid)":"2021-06-06T14:28:27.556Z","rssi":-60,"distance":0.9772372209558103,"channel":39},{"beacon_address":"20:18:FF:00:40:2D","system.totimestamp(timeuuid)":"2021-06-06T14:28:27.049Z","rssi":-70,"distance":0.9772372209558103,"channel":39},{"beacon_address":"20:18:FF:00:40:2D","system.totimestamp(timeuuid)":"2021-06-06T14:28:26.540Z","rssi":-63,"distance":0.9772372209558103,"channel":39},{"beacon_address":"20:18:FF:00:40:2D","system.totimestamp(timeuuid)":"2021-06-06T14:28:26.021Z","rssi":-69,"distance":1.2302687708123812,"channel":39},{"beacon_address":"20:18:FF:00:40:2D","system.totimestamp(timeuuid)":"2021-06-06T14:28:25.519Z","rssi":-77,"distance":1.1220184543019633,"channel":39},{"beacon_address":"20:18:FF:00:40:2D","system.totimestamp(timeuuid)":"2021-06-06T14:28:23.984Z","rssi":-60,"distance":0.8912509381337456,"channel":38},{"beacon_address":"20:18:FF:00:40:2D","system.totimestamp(timeuuid)":"2021-06-06T14:28:22.972Z","rssi":-70,"distance":1.1220184543019633,"channel":38},{"beacon_address":"20:18:FF:00:40:2D","system.totimestamp(timeuuid)":"2021-06-06T14:28:22.462Z","rssi":-73,"distance":1.0232929922807545,"channel":38},{"beacon_address":"20:18:FF:00:40:2D","system.totimestamp(timeuuid)":"2021-06-06T14:28:21.958Z","rssi":-65,"distance":1,"channel":38},{"beacon_address":"20:18:FF:00:40:2D","system.totimestamp(timeuuid)":"2021-06-06T14:28:21.450Z","rssi":-67,"distance":1.0964781961431846,"channel":38},{"beacon_address":"20:18:FF:00:40:2D","system.totimestamp(timeuuid)":"2021-06-06T14:28:20.420Z","rssi":-70,"distance":1.5848931924611136,"channel":37},{"beacon_address":"20:18:FF:00:40:2D","system.totimestamp(timeuuid)":"2021-06-06T14:28:19.909Z","rssi":-66,"distance":1.8197008586099839,"channel":37},{"beacon_address":"20:18:FF:00:40:2D","system.totimestamp(timeuuid)":"2021-06-06T14:28:19.398Z","rssi":-72,"distance":2.290867652767774,"channel":37},{"beacon_address":"20:18:FF:00:40:2D","system.totimestamp(timeuuid)":"2021-06-06T14:28:18.884Z","rssi":-69,"distance":2.51188643150958,"channel":37},{"beacon_address":"20:18:FF:00:40:2D","system.totimestamp(timeuuid)":"2021-06-06T14:28:18.373Z","rssi":-83,"distance":2.884031503126607,"channel":37},{"beacon_address":"20:18:FF:00:40:2D","system.totimestamp(timeuuid)":"2021-06-06T14:28:13.790Z","rssi":-76,"distance":2.398832919019489,"channel":39},{"beacon_address":"00:CD:FF:0E:5E:B9","system.totimestamp(timeuuid)":"2021-06-06T14:28:30.622Z","rssi":-85,"distance":3.890451449942805,"channel":37},{"beacon_address":"00:CD:FF:0E:5E:B9","system.totimestamp(timeuuid)":"2021-06-06T14:28:30.107Z","rssi":-85,"distance":2.951209226666388,"channel":37},{"beacon_address":"00:CD:FF:0E:5E:B9","system.totimestamp(timeuuid)":"2021-06-06T14:28:29.600Z","rssi":-74,"distance":2.398832919019489,"channel":37},{"beacon_address":"00:CD:FF:0E:5E:B9","system.totimestamp(timeuuid)":"2021-06-06T14:28:29.081Z","rssi":-80,"distance":2.6302679918953835,"channel":37},{"beacon_address":"00:CD:FF:0E:5E:B9","system.totimestamp(timeuuid)":"2021-06-06T14:28:28.568Z","rssi":-75,"distance":2.398832919019489,"channel":39},{"beacon_address":"00:CD:FF:0E:5E:B9","system.totimestamp(timeuuid)":"2021-06-06T14:28:28.065Z","rssi":-73,"distance":2.4547089156850297,"channel":39},{"beacon_address":"00:CD:FF:0E:5E:B9","system.totimestamp(timeuuid)":"2021-06-06T14:28:27.552Z","rssi":-76,"distance":3.548133892335755,"channel":39},{"beacon_address":"00:CD:FF:0E:5E:B9","system.totimestamp(timeuuid)":"2021-06-06T14:28:27.044Z","rssi":-78,"distance":3.1622776601683795,"channel":39},{"beacon_address":"00:CD:FF:0E:5E:B9","system.totimestamp(timeuuid)":"2021-06-06T14:28:26.533Z","rssi":-76,"distance":2.951209226666388,"channel":39},{"beacon_address":"00:CD:FF:0E:5E:B9","system.totimestamp(timeuuid)":"2021-06-06T14:28:26.019Z","rssi":-76,"distance":2.951209226666388,"channel":39},{"beacon_address":"00:CD:FF:0E:5E:B9","system.totimestamp(timeuuid)":"2021-06-06T14:28:25.512Z","rssi":-89,"distance":2.951209226666388,"channel":39},{"beacon_address":"00:CD:FF:0E:5E:B9","system.totimestamp(timeuuid)":"2021-06-06T14:28:25.003Z","rssi":-71,"distance":2.1877616239495516,"channel":39},{"beacon_address":"00:CD:FF:0E:5E:B9","system.totimestamp(timeuuid)":"2021-06-06T14:28:24.488Z","rssi":-75,"distance":2.4547089156850297,"channel":38},{"beacon_address":"00:CD:FF:0E:5E:B9","system.totimestamp(timeuuid)":"2021-06-06T14:28:23.981Z","rssi":-76,"distance":2.398832919019489,"channel":38},{"beacon_address":"00:CD:FF:0E:5E:B9","system.totimestamp(timeuuid)":"2021-06-06T14:28:21.950Z","rssi":-76,"distance":2.089296130854041,"channel":38},{"beacon_address":"00:CD:FF:0E:5E:B9","system.totimestamp(timeuuid)":"2021-06-06T14:28:21.443Z","rssi":-76,"distance":2.137962089502231,"channel":38},{"beacon_address":"00:CD:FF:0E:5E:B9","system.totimestamp(timeuuid)":"2021-06-06T14:28:20.932Z","rssi":-76,"distance":1.9498445997580447,"channel":38},{"beacon_address":"00:CD:FF:0E:5E:B9","system.totimestamp(timeuuid)":"2021-06-06T14:28:20.414Z","rssi":-74,"distance":1.7782794100389228,"channel":37},{"beacon_address":"00:CD:FF:0E:5E:B9","system.totimestamp(timeuuid)":"2021-06-06T14:28:19.393Z","rssi":-70,"distance":1.6982436524617432,"channel":37},{"beacon_address":"00:CD:FF:0E:5E:B9","system.totimestamp(timeuuid)":"2021-06-06T14:28:18.369Z","rssi":-77,"distance":1.8197008586099839,"channel":37},{"beacon_address":"20:18:FF:00:3F:E7","system.totimestamp(timeuuid)":"2021-06-06T14:28:31.149Z","rssi":-90,"distance":6.760829753919814,"channel":37},{"beacon_address":"20:18:FF:00:3F:E7","system.totimestamp(timeuuid)":"2021-06-06T14:28:30.634Z","rssi":-86,"distance":5.011872336272722,"channel":37},{"beacon_address":"20:18:FF:00:3F:E7","system.totimestamp(timeuuid)":"2021-06-06T14:28:30.115Z","rssi":-80,"distance":5.011872336272722,"channel":37},{"beacon_address":"20:18:FF:00:3F:E7","system.totimestamp(timeuuid)":"2021-06-06T14:28:29.614Z","rssi":-83,"distance":5.888436553555893,"channel":37},{"beacon_address":"20:18:FF:00:3F:E7","system.totimestamp(timeuuid)":"2021-06-06T14:28:29.089Z","rssi":-74,"distance":7.943282347242816,"channel":37},{"beacon_address":"20:18:FF:00:3F:E7","system.totimestamp(timeuuid)":"2021-06-06T14:28:28.073Z","rssi":-77,"distance":8.709635899560803,"channel":39},{"beacon_address":"20:18:FF:00:3F:E7","system.totimestamp(timeuuid)":"2021-06-06T14:28:27.055Z","rssi":-86,"distance":9.332543007969917,"channel":39},{"beacon_address":"20:18:FF:00:3F:E7","system.totimestamp(timeuuid)":"2021-06-06T14:28:26.548Z","rssi":-87,"distance":7.943282347242816,"channel":39},{"beacon_address":"20:18:FF:00:3F:E7","system.totimestamp(timeuuid)":"2021-06-06T14:28:26.026Z","rssi":-96,"distance":6.456542290346557,"channel":39},{"beacon_address":"20:18:FF:00:3F:E7","system.totimestamp(timeuuid)":"2021-06-06T14:28:25.529Z","rssi":-78,"distance":4.073802778041128,"channel":39},{"beacon_address":"20:18:FF:00:3F:E7","system.totimestamp(timeuuid)":"2021-06-06T14:28:25.014Z","rssi":-80,"distance":4.466835921509632,"channel":39},{"beacon_address":"20:18:FF:00:3F:E7","system.totimestamp(timeuuid)":"2021-06-06T14:28:24.497Z","rssi":-79,"distance":4.570881896148752,"channel":38},{"beacon_address":"20:18:FF:00:3F:E7","system.totimestamp(timeuuid)":"2021-06-06T14:28:23.987Z","rssi":-78,"distance":5.24807460249773,"channel":38},{"beacon_address":"20:18:FF:00:3F:E7","system.totimestamp(timeuuid)":"2021-06-06T14:28:23.478Z","rssi":-76,"distance":5.754399373371571,"channel":38},{"beacon_address":"20:18:FF:00:3F:E7","system.totimestamp(timeuuid)":"2021-06-06T14:28:22.979Z","rssi":-82,"distance":7.079457843841379,"channel":38},{"beacon_address":"20:18:FF:00:3F:E7","system.totimestamp(timeuuid)":"2021-06-06T14:28:22.470Z","rssi":-81,"distance":7.7624711662869155,"channel":38},{"beacon_address":"20:18:FF:00:3F:E7","system.totimestamp(timeuuid)":"2021-06-06T14:28:21.966Z","rssi":-85,"distance":10.232929922807546,"channel":38},{"beacon_address":"20:18:FF:00:3F:E7","system.totimestamp(timeuuid)":"2021-06-06T14:28:21.458Z","rssi":-82,"distance":7.7624711662869155,"channel":38},{"beacon_address":"20:18:FF:00:3F:E7","system.totimestamp(timeuuid)":"2021-06-06T14:28:20.944Z","rssi":-85,"distance":6.918309709189363,"channel":38},{"beacon_address":"20:18:FF:00:3F:E7","system.totimestamp(timeuuid)":"2021-06-06T14:28:20.428Z","rssi":-86,"distance":4.7863009232263805,"channel":37},{"beacon_address":"20:18:FF:00:3F:E7","system.totimestamp(timeuuid)":"2021-06-06T14:28:19.917Z","rssi":-93,"distance":2.884031503126607,"channel":37},{"beacon_address":"20:18:FF:00:3F:E7","system.totimestamp(timeuuid)":"2021-06-06T14:28:19.405Z","rssi":-73,"distance":1.4791083881682083,"channel":37},{"beacon_address":"20:18:FF:00:3F:E7","system.totimestamp(timeuuid)":"2021-06-06T14:28:18.895Z","rssi":-77,"distance":1.202264434617412,"channel":37},{"beacon_address":"20:18:FF:00:3F:E7","system.totimestamp(timeuuid)":"2021-06-06T14:28:18.392Z","rssi":-69,"distance":0.8912509381337456,"channel":37},{"beacon_address":"20:18:FF:00:3F:E7","system.totimestamp(timeuuid)":"2021-06-06T14:28:13.802Z","rssi":-64,"distance":0.7943282347242815,"channel":39},{"beacon_address":"20:18:FF:00:40:07","system.totimestamp(timeuuid)":"2021-06-06T14:28:31.150Z","rssi":-87,"distance":4.677351412871984,"channel":37},{"beacon_address":"20:18:FF:00:40:07","system.totimestamp(timeuuid)":"2021-06-06T14:28:30.636Z","rssi":-80,"distance":2.8183829312644537,"channel":37},{"beacon_address":"20:18:FF:00:40:07","system.totimestamp(timeuuid)":"2021-06-06T14:28:30.118Z","rssi":-80,"distance":2.398832919019489,"channel":37},{"beacon_address":"20:18:FF:00:40:07","system.totimestamp(timeuuid)":"2021-06-06T14:28:29.615Z","rssi":-82,"distance":1.8197008586099839,"channel":37},{"beacon_address":"20:18:FF:00:40:07","system.totimestamp(timeuuid)":"2021-06-06T14:28:29.091Z","rssi":-68,"distance":1.2589254117941673,"channel":37},{"beacon_address":"20:18:FF:00:40:07","system.totimestamp(timeuuid)":"2021-06-06T14:28:28.574Z","rssi":-65,"distance":1.8620871366628686,"channel":39},{"beacon_address":"20:18:FF:00:40:07","system.totimestamp(timeuuid)":"2021-06-06T14:28:28.074Z","rssi":-73,"distance":1.905460717963246,"channel":39},{"beacon_address":"20:18:FF:00:40:07","system.totimestamp(timeuuid)":"2021-06-06T14:28:27.564Z","rssi":-68,"distance":1.8197008586099839,"channel":39},{"beacon_address":"20:18:FF:00:40:07","system.totimestamp(timeuuid)":"2021-06-06T14:28:27.057Z","rssi":-66,"distance":2.1877616239495516,"channel":39},{"beacon_address":"20:18:FF:00:40:07","system.totimestamp(timeuuid)":"2021-06-06T14:28:26.549Z","rssi":-85,"distance":2.8183829312644537,"channel":39},{"beacon_address":"20:18:FF:00:40:07","system.totimestamp(timeuuid)":"2021-06-06T14:28:26.026Z","rssi":-66,"distance":2.51188643150958,"channel":39},{"beacon_address":"20:18:FF:00:40:07","system.totimestamp(timeuuid)":"2021-06-06T14:28:25.530Z","rssi":-71,"distance":2.8183829312644537,"channel":39},{"beacon_address":"20:18:FF:00:40:07","system.totimestamp(timeuuid)":"2021-06-06T14:28:25.015Z","rssi":-76,"distance":3.0199517204020143,"channel":39},{"beacon_address":"20:18:FF:00:40:07","system.totimestamp(timeuuid)":"2021-06-06T14:28:23.988Z","rssi":-77,"distance":3.2359365692962836,"channel":38},{"beacon_address":"20:18:FF:00:40:07","system.totimestamp(timeuuid)":"2021-06-06T14:28:22.981Z","rssi":-80,"distance":2.398832919019489,"channel":38},{"beacon_address":"20:18:FF:00:40:07","system.totimestamp(timeuuid)":"2021-06-06T14:28:22.472Z","rssi":-71,"distance":1.7782794100389228,"channel":38},{"beacon_address":"20:18:FF:00:40:07","system.totimestamp(timeuuid)":"2021-06-06T14:28:21.968Z","rssi":-74,"distance":1.6595869074375618,"channel":38},{"beacon_address":"20:18:FF:00:40:07","system.totimestamp(timeuuid)":"2021-06-06T14:28:21.460Z","rssi":-79,"distance":1.3489628825916529,"channel":38},{"beacon_address":"20:18:FF:00:40:07","system.totimestamp(timeuuid)":"2021-06-06T14:28:20.946Z","rssi":-64,"distance":1.0471285480509003,"channel":38},{"beacon_address":"20:18:FF:00:40:07","system.totimestamp(timeuuid)":"2021-06-06T14:28:20.429Z","rssi":-67,"distance":1.6595869074375618,"channel":37},{"beacon_address":"20:18:FF:00:40:07","system.totimestamp(timeuuid)":"2021-06-06T14:28:19.919Z","rssi":-68,"distance":2.691534803926914,"channel":37},{"beacon_address":"20:18:FF:00:40:07","system.totimestamp(timeuuid)":"2021-06-06T14:28:18.898Z","rssi":-65,"distance":4.570881896148752,"channel":37},{"beacon_address":"20:18:FF:00:40:07","system.totimestamp(timeuuid)":"2021-06-06T14:28:18.394Z","rssi":-68,"distance":7.585775750291832,"channel":37},{"beacon_address":"20:18:FF:00:40:07","system.totimestamp(timeuuid)":"2021-06-06T14:28:13.805Z","rssi":-84,"distance":12.022644346174118,"channel":39},{"beacon_address":"20:18:FF:00:40:2C","system.totimestamp(timeuuid)":"2021-06-06T14:28:31.142Z","rssi":-71,"distance":2.398832919019489,"channel":37},{"beacon_address":"20:18:FF:00:40:2C","system.totimestamp(timeuuid)":"2021-06-06T14:28:30.629Z","rssi":-90,"distance":2.089296130854041,"channel":37},{"beacon_address":"20:18:FF:00:40:2C","system.totimestamp(timeuuid)":"2021-06-06T14:28:30.110Z","rssi":-78,"distance":1.2882495516931345,"channel":37},{"beacon_address":"20:18:FF:00:40:2C","system.totimestamp(timeuuid)":"2021-06-06T14:28:29.609Z","rssi":-70,"distance":0.7585775750291832,"channel":37},{"beacon_address":"20:18:FF:00:40:2C","system.totimestamp(timeuuid)":"2021-06-06T14:28:28.571Z","rssi":-64,"distance":0.6025595860743579,"channel":39},{"beacon_address":"20:18:FF:00:40:2C","system.totimestamp(timeuuid)":"2021-06-06T14:28:27.559Z","rssi":-65,"distance":0.5248074602497725,"channel":39},{"beacon_address":"20:18:FF:00:40:2C","system.totimestamp(timeuuid)":"2021-06-06T14:28:27.050Z","rssi":-69,"distance":0.512861383991365,"channel":39},{"beacon_address":"20:18:FF:00:40:2C","system.totimestamp(timeuuid)":"2021-06-06T14:28:26.023Z","rssi":-55,"distance":0.6025595860743579,"channel":39},{"beacon_address":"20:18:FF:00:40:2C","system.totimestamp(timeuuid)":"2021-06-06T14:28:25.523Z","rssi":-60,"distance":0.9332543007969917,"channel":39},{"beacon_address":"20:18:FF:00:40:2C","system.totimestamp(timeuuid)":"2021-06-06T14:28:25.008Z","rssi":-58,"distance":0.9549925860214353,"channel":39},{"beacon_address":"20:18:FF:00:40:2C","system.totimestamp(timeuuid)":"2021-06-06T14:28:24.492Z","rssi":-64,"distance":1.0715193052376057,"channel":38},{"beacon_address":"20:18:FF:00:40:2C","system.totimestamp(timeuuid)":"2021-06-06T14:28:23.985Z","rssi":-76,"distance":1.0715193052376057,"channel":38},{"beacon_address":"20:18:FF:00:40:2C","system.totimestamp(timeuuid)":"2021-06-06T14:28:23.473Z","rssi":-74,"distance":1,"channel":38},{"beacon_address":"20:18:FF:00:40:2C","system.totimestamp(timeuuid)":"2021-06-06T14:28:22.974Z","rssi":-61,"distance":0.9549925860214353,"channel":38},{"beacon_address":"20:18:FF:00:40:2C","system.totimestamp(timeuuid)":"2021-06-06T14:28:22.464Z","rssi":-63,"distance":1.2589254117941673,"channel":38},{"beacon_address":"20:18:FF:00:40:2C","system.totimestamp(timeuuid)":"2021-06-06T14:28:21.960Z","rssi":-64,"distance":1.7782794100389228,"channel":38},{"beacon_address":"20:18:FF:00:40:2C","system.totimestamp(timeuuid)":"2021-06-06T14:28:21.452Z","rssi":-73,"distance":2.691534803926914,"channel":38},{"beacon_address":"20:18:FF:00:40:2C","system.totimestamp(timeuuid)":"2021-06-06T14:28:20.937Z","rssi":-72,"distance":3.311311214825913,"channel":38},{"beacon_address":"20:18:FF:00:40:2C","system.totimestamp(timeuuid)":"2021-06-06T14:28:20.423Z","rssi":-73,"distance":4.168693834703357,"channel":37},{"beacon_address":"20:18:FF:00:40:2C","system.totimestamp(timeuuid)":"2021-06-06T14:28:18.377Z","rssi":-78,"distance":4.89778819368446,"channel":37},{"beacon_address":"20:18:FF:00:40:2C","system.totimestamp(timeuuid)":"2021-06-06T14:28:13.793Z","rssi":-82,"distance":5.24807460249773,"channel":39},{"beacon_address":"20:18:FF:00:3F:E4","system.totimestamp(timeuuid)":"2021-06-06T14:28:31.132Z","rssi":-86,"distance":4.570881896148752,"channel":37},{"beacon_address":"20:18:FF:00:3F:E4","system.totimestamp(timeuuid)":"2021-06-06T14:28:30.619Z","rssi":-82,"distance":4.2657951880159235,"channel":37},{"beacon_address":"20:18:FF:00:3F:E4","system.totimestamp(timeuuid)":"2021-06-06T14:28:29.597Z","rssi":-73,"distance":4.365158322401658,"channel":37},{"beacon_address":"20:18:FF:00:3F:E4","system.totimestamp(timeuuid)":"2021-06-06T14:28:28.567Z","rssi":-75,"distance":5.128613839913651,"channel":39},{"beacon_address":"20:18:FF:00:3F:E4","system.totimestamp(timeuuid)":"2021-06-06T14:28:28.062Z","rssi":-80,"distance":6.918309709189363,"channel":39},{"beacon_address":"20:18:FF:00:3F:E4","system.totimestamp(timeuuid)":"2021-06-06T14:28:27.550Z","rssi":-83,"distance":6.918309709189363,"channel":39},{"beacon_address":"20:18:FF:00:3F:E4","system.totimestamp(timeuuid)":"2021-06-06T14:28:27.041Z","rssi":-83,"distance":6.165950018614819,"channel":39},{"beacon_address":"20:18:FF:00:3F:E4","system.totimestamp(timeuuid)":"2021-06-06T14:28:26.531Z","rssi":-80,"distance":5.370317963702524,"channel":39},{"beacon_address":"20:18:FF:00:3F:E4","system.totimestamp(timeuuid)":"2021-06-06T14:28:26.018Z","rssi":-88,"distance":5.24807460249773,"channel":39},{"beacon_address":"20:18:FF:00:3F:E4","system.totimestamp(timeuuid)":"2021-06-06T14:28:25.509Z","rssi":-80,"distance":4.570881896148752,"channel":39},{"beacon_address":"20:18:FF:00:3F:E4","system.totimestamp(timeuuid)":"2021-06-06T14:28:24.999Z","rssi":-78,"distance":4.7863009232263805,"channel":39},{"beacon_address":"20:18:FF:00:3F:E4","system.totimestamp(timeuuid)":"2021-06-06T14:28:24.486Z","rssi":-77,"distance":4.677351412871984,"channel":38},{"beacon_address":"20:18:FF:00:3F:E4","system.totimestamp(timeuuid)":"2021-06-06T14:28:23.978Z","rssi":-79,"distance":6.918309709189363,"channel":38},{"beacon_address":"20:18:FF:00:3F:E4","system.totimestamp(timeuuid)":"2021-06-06T14:28:23.469Z","rssi":-82,"distance":10.471285480509001,"channel":38},{"beacon_address":"20:18:FF:00:3F:E4","system.totimestamp(timeuuid)":"2021-06-06T14:28:22.458Z","rssi":-82,"distance":9.332543007969917,"channel":38},{"beacon_address":"20:18:FF:00:3F:E4","system.totimestamp(timeuuid)":"2021-06-06T14:28:21.948Z","rssi":-77,"distance":8.51138038202376,"channel":38},{"beacon_address":"20:18:FF:00:3F:E4","system.totimestamp(timeuuid)":"2021-06-06T14:28:21.439Z","rssi":-94,"distance":9.120108393559102,"channel":38},{"beacon_address":"20:18:FF:00:3F:E4","system.totimestamp(timeuuid)":"2021-06-06T14:28:20.927Z","rssi":-97,"distance":5.24807460249773,"channel":38},{"beacon_address":"20:18:FF:00:3F:E4","system.totimestamp(timeuuid)":"2021-06-06T14:28:20.412Z","rssi":-77,"distance":2.884031503126607,"channel":37},{"beacon_address":"20:18:FF:00:3F:E4","system.totimestamp(timeuuid)":"2021-06-06T14:28:19.902Z","rssi":-78,"distance":3.0199517204020143,"channel":37},{"beacon_address":"20:18:FF:00:3F:E4","system.totimestamp(timeuuid)":"2021-06-06T14:28:19.390Z","rssi":-80,"distance":3.1622776601683795,"channel":37},{"beacon_address":"20:18:FF:00:3F:E4","system.totimestamp(timeuuid)":"2021-06-06T14:28:18.878Z","rssi":-70,"distance":3.1622776601683795,"channel":37},{"beacon_address":"20:18:FF:00:3F:E4","system.totimestamp(timeuuid)":"2021-06-06T14:28:17.858Z","rssi":-71,"distance":3.9810717055349722,"channel":37},{"beacon_address":"20:18:FF:00:40:20","system.totimestamp(timeuuid)":"2021-06-06T14:28:31.127Z","rssi":-70,"distance":0.8912509381337456,"channel":37},{"beacon_address":"20:18:FF:00:40:20","system.totimestamp(timeuuid)":"2021-06-06T14:28:30.613Z","rssi":-61,"distance":0.8709635899560804,"channel":37},{"beacon_address":"20:18:FF:00:40:20","system.totimestamp(timeuuid)":"2021-06-06T14:28:30.101Z","rssi":-60,"distance":0.9772372209558103,"channel":37},{"beacon_address":"20:18:FF:00:40:20","system.totimestamp(timeuuid)":"2021-06-06T14:28:29.592Z","rssi":-60,"distance":1.4454397707459279,"channel":37},{"beacon_address":"20:18:FF:00:40:20","system.totimestamp(timeuuid)":"2021-06-06T14:28:29.076Z","rssi":-64,"distance":1.9952623149688795,"channel":37},{"beacon_address":"20:18:FF:00:40:20","system.totimestamp(timeuuid)":"2021-06-06T14:28:28.565Z","rssi":-69,"distance":2.137962089502231,"channel":39},{"beacon_address":"20:18:FF:00:40:20","system.totimestamp(timeuuid)":"2021-06-06T14:28:28.058Z","rssi":-66,"distance":2.4547089156850297,"channel":39},{"beacon_address":"20:18:FF:00:40:20","system.totimestamp(timeuuid)":"2021-06-06T14:28:27.546Z","rssi":-77,"distance":2.089296130854041,"channel":39},{"beacon_address":"20:18:FF:00:40:20","system.totimestamp(timeuuid)":"2021-06-06T14:28:27.036Z","rssi":-74,"distance":1.5848931924611136,"channel":39},{"beacon_address":"20:18:FF:00:40:20","system.totimestamp(timeuuid)":"2021-06-06T14:28:26.526Z","rssi":-67,"distance":1.4454397707459279,"channel":39},{"beacon_address":"20:18:FF:00:40:20","system.totimestamp(timeuuid)":"2021-06-06T14:28:26.016Z","rssi":-75,"distance":1.318256738556408,"channel":39},{"beacon_address":"20:18:FF:00:40:20","system.totimestamp(timeuuid)":"2021-06-06T14:28:25.504Z","rssi":-59,"distance":1.148153621496883,"channel":39},{"beacon_address":"20:18:FF:00:40:20","system.totimestamp(timeuuid)":"2021-06-06T14:28:24.994Z","rssi":-65,"distance":1.9952623149688795,"channel":39},{"beacon_address":"20:18:FF:00:40:20","system.totimestamp(timeuuid)":"2021-06-06T14:28:24.482Z","rssi":-70,"distance":2.04173794466953,"channel":38},{"beacon_address":"20:18:FF:00:40:20","system.totimestamp(timeuuid)":"2021-06-06T14:28:23.976Z","rssi":-63,"distance":2.04173794466953,"channel":38},{"beacon_address":"20:18:FF:00:40:20","system.totimestamp(timeuuid)":"2021-06-06T14:28:23.466Z","rssi":-69,"distance":2.1877616239495516,"channel":38},{"beacon_address":"20:18:FF:00:40:20","system.totimestamp(timeuuid)":"2021-06-06T14:28:22.962Z","rssi":-83,"distance":2.290867652767774,"channel":38},{"beacon_address":"20:18:FF:00:40:20","system.totimestamp(timeuuid)":"2021-06-06T14:28:22.453Z","rssi":-66,"distance":1.737800828749375,"channel":38},{"beacon_address":"20:18:FF:00:40:20","system.totimestamp(timeuuid)":"2021-06-06T14:28:21.943Z","rssi":-70,"distance":1.9952623149688795,"channel":38},{"beacon_address":"20:18:FF:00:40:20","system.totimestamp(timeuuid)":"2021-06-06T14:28:21.431Z","rssi":-66,"distance":2.137962089502231,"channel":38},{"beacon_address":"20:18:FF:00:40:20","system.totimestamp(timeuuid)":"2021-06-06T14:28:20.920Z","rssi":-71,"distance":2.8183829312644537,"channel":38},{"beacon_address":"20:18:FF:00:40:20","system.totimestamp(timeuuid)":"2021-06-06T14:28:20.407Z","rssi":-71,"distance":3.890451449942805,"channel":37},{"beacon_address":"20:18:FF:00:40:20","system.totimestamp(timeuuid)":"2021-06-06T14:28:19.894Z","rssi":-72,"distance":5.495408738576244,"channel":37},{"beacon_address":"20:18:FF:00:40:20","system.totimestamp(timeuuid)":"2021-06-06T14:28:19.385Z","rssi":-73,"distance":6.760829753919814,"channel":37},{"beacon_address":"20:18:FF:00:40:20","system.totimestamp(timeuuid)":"2021-06-06T14:28:18.870Z","rssi":-78,"distance":8.317637711026714,"channel":37},{"beacon_address":"20:18:FF:00:40:20","system.totimestamp(timeuuid)":"2021-06-06T14:28:18.359Z","rssi":-85,"distance":8.912509381337454,"channel":37},{"beacon_address":"20:18:FF:00:40:20","system.totimestamp(timeuuid)":"2021-06-06T14:28:17.849Z","rssi":-86,"distance":8.317637711026714,"channel":37},{"beacon_address":"20:18:FF:00:40:20","system.totimestamp(timeuuid)":"2021-06-06T14:28:13.754Z","rssi":-81,"distance":7.585775750291832,"channel":39},{"beacon_address":"20:18:FF:00:40:2E","system.totimestamp(timeuuid)":"2021-06-06T14:28:31.145Z","rssi":-78,"distance":0.9549925860214353,"channel":37},{"beacon_address":"20:18:FF:00:40:2E","system.totimestamp(timeuuid)":"2021-06-06T14:28:30.631Z","rssi":-68,"distance":0.8511380382023759,"channel":37},{"beacon_address":"20:18:FF:00:40:2E","system.totimestamp(timeuuid)":"2021-06-06T14:28:30.112Z","rssi":-62,"distance":1,"channel":37},{"beacon_address":"20:18:FF:00:40:2E","system.totimestamp(timeuuid)":"2021-06-06T14:28:29.611Z","rssi":-53,"distance":1.318256738556408,"channel":37},{"beacon_address":"20:18:FF:00:40:2E","system.totimestamp(timeuuid)":"2021-06-06T14:28:28.572Z","rssi":-67,"distance":2.04173794466953,"channel":39},{"beacon_address":"20:18:FF:00:40:2E","system.totimestamp(timeuuid)":"2021-06-06T14:28:28.069Z","rssi":-73,"distance":1.8197008586099839,"channel":39},{"beacon_address":"20:18:FF:00:40:2E","system.totimestamp(timeuuid)":"2021-06-06T14:28:27.561Z","rssi":-75,"distance":1.6982436524617432,"channel":39},{"beacon_address":"20:18:FF:00:40:2E","system.totimestamp(timeuuid)":"2021-06-06T14:28:27.052Z","rssi":-74,"distance":1.8197008586099839,"channel":39},{"beacon_address":"20:18:FF:00:40:2E","system.totimestamp(timeuuid)":"2021-06-06T14:28:26.543Z","rssi":-72,"distance":1.5488166189124808,"channel":39},{"beacon_address":"20:18:FF:00:40:2E","system.totimestamp(timeuuid)":"2021-06-06T14:28:26.024Z","rssi":-62,"distance":1.7782794100389228,"channel":39},{"beacon_address":"20:18:FF:00:40:2E","system.totimestamp(timeuuid)":"2021-06-06T14:28:25.526Z","rssi":-70,"distance":2.089296130854041,"channel":39},{"beacon_address":"20:18:FF:00:40:2E","system.totimestamp(timeuuid)":"2021-06-06T14:28:25.010Z","rssi":-78,"distance":2.137962089502231,"channel":39},{"beacon_address":"20:18:FF:00:40:2E","system.totimestamp(timeuuid)":"2021-06-06T14:28:24.494Z","rssi":-67,"distance":1.905460717963246,"channel":38},{"beacon_address":"20:18:FF:00:40:2E","system.totimestamp(timeuuid)":"2021-06-06T14:28:23.986Z","rssi":-78,"distance":2.6302679918953835,"channel":38},{"beacon_address":"20:18:FF:00:40:2E","system.totimestamp(timeuuid)":"2021-06-06T14:28:23.475Z","rssi":-69,"distance":1.905460717963246,"channel":38},{"beacon_address":"20:18:FF:00:40:2E","system.totimestamp(timeuuid)":"2021-06-06T14:28:22.467Z","rssi":-71,"distance":1.513561248436207,"channel":38},{"beacon_address":"20:18:FF:00:40:2E","system.totimestamp(timeuuid)":"2021-06-06T14:28:21.963Z","rssi":-73,"distance":1.318256738556408,"channel":38},{"beacon_address":"20:18:FF:00:40:2E","system.totimestamp(timeuuid)":"2021-06-06T14:28:21.454Z","rssi":-81,"distance":1.0232929922807545,"channel":38},{"beacon_address":"20:18:FF:00:40:2E","system.totimestamp(timeuuid)":"2021-06-06T14:28:20.940Z","rssi":-64,"distance":0.6456542290346557,"channel":38},{"beacon_address":"20:18:FF:00:40:2E","system.totimestamp(timeuuid)":"2021-06-06T14:28:19.912Z","rssi":-59,"distance":0.7079457843841379,"channel":37},{"beacon_address":"20:18:FF:00:40:2E","system.totimestamp(timeuuid)":"2021-06-06T14:28:19.400Z","rssi":-65,"distance":0.8709635899560804,"channel":37},{"beacon_address":"20:18:FF:00:40:2E","system.totimestamp(timeuuid)":"2021-06-06T14:28:18.889Z","rssi":-62,"distance":0.9332543007969917,"channel":37},{"beacon_address":"20:18:FF:00:40:2E","system.totimestamp(timeuuid)":"2021-06-06T14:28:18.381Z","rssi":-61,"distance":1.0715193052376057,"channel":37},{"beacon_address":"20:18:FF:00:40:2E","system.totimestamp(timeuuid)":"2021-06-06T14:28:13.796Z","rssi":-68,"distance":1.2589254117941673,"channel":39},{"beacon_address":"20:18:FF:00:40:02","system.totimestamp(timeuuid)":"2021-06-06T14:28:31.135Z","rssi":-87,"distance":4.073802778041128,"channel":37},{"beacon_address":"20:18:FF:00:40:02","system.totimestamp(timeuuid)":"2021-06-06T14:28:30.624Z","rssi":-82,"distance":3.715352290971728,"channel":37},{"beacon_address":"20:18:FF:00:40:02","system.totimestamp(timeuuid)":"2021-06-06T14:28:30.109Z","rssi":-83,"distance":3.311311214825913,"channel":37},{"beacon_address":"20:18:FF:00:40:02","system.totimestamp(timeuuid)":"2021-06-06T14:28:29.605Z","rssi":-69,"distance":2.8183829312644537,"channel":37},{"beacon_address":"20:18:FF:00:40:02","system.totimestamp(timeuuid)":"2021-06-06T14:28:28.569Z","rssi":-70,"distance":3.630780547701015,"channel":39},{"beacon_address":"20:18:FF:00:40:02","system.totimestamp(timeuuid)":"2021-06-06T14:28:27.554Z","rssi":-83,"distance":3.630780547701015,"channel":39},{"beacon_address":"20:18:FF:00:40:02","system.totimestamp(timeuuid)":"2021-06-06T14:28:27.047Z","rssi":-77,"distance":2.691534803926914,"channel":39},{"beacon_address":"20:18:FF:00:40:02","system.totimestamp(timeuuid)":"2021-06-06T14:28:26.536Z","rssi":-76,"distance":2.2387211385683394,"channel":39},{"beacon_address":"20:18:FF:00:40:02","system.totimestamp(timeuuid)":"2021-06-06T14:28:26.020Z","rssi":-80,"distance":2.3442288153199238,"channel":39},{"beacon_address":"20:18:FF:00:40:02","system.totimestamp(timeuuid)":"2021-06-06T14:28:25.006Z","rssi":-70,"distance":1.905460717963246,"channel":39},{"beacon_address":"20:18:FF:00:40:02","system.totimestamp(timeuuid)":"2021-06-06T14:28:24.490Z","rssi":-70,"distance":2.2387211385683394,"channel":38},{"beacon_address":"20:18:FF:00:40:02","system.totimestamp(timeuuid)":"2021-06-06T14:28:23.983Z","rssi":-69,"distance":2.4547089156850297,"channel":38},{"beacon_address":"20:18:FF:00:40:02","system.totimestamp(timeuuid)":"2021-06-06T14:28:23.470Z","rssi":-78,"distance":3.0199517204020143,"channel":38},{"beacon_address":"20:18:FF:00:40:02","system.totimestamp(timeuuid)":"2021-06-06T14:28:22.968Z","rssi":-71,"distance":2.51188643150958,"channel":38},{"beacon_address":"20:18:FF:00:40:02","system.totimestamp(timeuuid)":"2021-06-06T14:28:22.459Z","rssi":-77,"distance":3.0902954325135896,"channel":38},{"beacon_address":"20:18:FF:00:40:02","system.totimestamp(timeuuid)":"2021-06-06T14:28:21.953Z","rssi":-74,"distance":2.8183829312644537,"channel":38},{"beacon_address":"20:18:FF:00:40:02","system.totimestamp(timeuuid)":"2021-06-06T14:28:21.447Z","rssi":-78,"distance":2.04173794466953,"channel":38},{"beacon_address":"20:18:FF:00:40:02","system.totimestamp(timeuuid)":"2021-06-06T14:28:20.935Z","rssi":-70,"distance":1.6595869074375618,"channel":38},{"beacon_address":"20:18:FF:00:40:02","system.totimestamp(timeuuid)":"2021-06-06T14:28:20.418Z","rssi":-80,"distance":1.6218100973589304,"channel":37},{"beacon_address":"20:18:FF:00:40:02","system.totimestamp(timeuuid)":"2021-06-06T14:28:19.906Z","rssi":-73,"distance":1.2589254117941673,"channel":37},{"beacon_address":"20:18:FF:00:40:02","system.totimestamp(timeuuid)":"2021-06-06T14:28:19.395Z","rssi":-60,"distance":1.148153621496883,"channel":37},{"beacon_address":"20:18:FF:00:40:02","system.totimestamp(timeuuid)":"2021-06-06T14:28:13.787Z","rssi":-69,"distance":1.4125375446227544,"channel":39},{"beacon_address":"20:18:FF:00:40:08","system.totimestamp(timeuuid)":"2021-06-06T14:28:31.147Z","rssi":-77,"distance":3.2359365692962836,"channel":37},{"beacon_address":"20:18:FF:00:40:08","system.totimestamp(timeuuid)":"2021-06-06T14:28:30.633Z","rssi":-74,"distance":2.4547089156850297,"channel":37},{"beacon_address":"20:18:FF:00:40:08","system.totimestamp(timeuuid)":"2021-06-06T14:28:30.113Z","rssi":-71,"distance":2.137962089502231,"channel":37},{"beacon_address":"20:18:FF:00:40:08","system.totimestamp(timeuuid)":"2021-06-06T14:28:29.612Z","rssi":-91,"distance":2.089296130854041,"channel":37},{"beacon_address":"20:18:FF:00:40:08","system.totimestamp(timeuuid)":"2021-06-06T14:28:29.088Z","rssi":-68,"distance":1.1748975549395304,"channel":37},{"beacon_address":"20:18:FF:00:40:08","system.totimestamp(timeuuid)":"2021-06-06T14:28:28.573Z","rssi":-65,"distance":1.3489628825916529,"channel":39},{"beacon_address":"20:18:FF:00:40:08","system.totimestamp(timeuuid)":"2021-06-06T14:28:28.071Z","rssi":-68,"distance":1.513561248436207,"channel":39},{"beacon_address":"20:18:FF:00:40:08","system.totimestamp(timeuuid)":"2021-06-06T14:28:27.563Z","rssi":-70,"distance":1.6218100973589304,"channel":39},{"beacon_address":"20:18:FF:00:40:08","system.totimestamp(timeuuid)":"2021-06-06T14:28:27.054Z","rssi":-66,"distance":1.9952623149688795,"channel":39},{"beacon_address":"20:18:FF:00:40:08","system.totimestamp(timeuuid)":"2021-06-06T14:28:26.545Z","rssi":-74,"distance":2.1877616239495516,"channel":39},{"beacon_address":"20:18:FF:00:40:08","system.totimestamp(timeuuid)":"2021-06-06T14:28:26.025Z","rssi":-70,"distance":2.1877616239495516,"channel":39},{"beacon_address":"20:18:FF:00:40:08","system.totimestamp(timeuuid)":"2021-06-06T14:28:25.012Z","rssi":-71,"distance":2.2387211385683394,"channel":39},{"beacon_address":"20:18:FF:00:40:08","system.totimestamp(timeuuid)":"2021-06-06T14:28:24.496Z","rssi":-79,"distance":2.398832919019489,"channel":38},{"beacon_address":"20:18:FF:00:40:08","system.totimestamp(timeuuid)":"2021-06-06T14:28:23.986Z","rssi":-70,"distance":1.737800828749375,"channel":38},{"beacon_address":"20:18:FF:00:40:08","system.totimestamp(timeuuid)":"2021-06-06T14:28:23.476Z","rssi":-74,"distance":1.5488166189124808,"channel":38},{"beacon_address":"20:18:FF:00:40:08","system.totimestamp(timeuuid)":"2021-06-06T14:28:22.977Z","rssi":-71,"distance":1.5488166189124808,"channel":38},{"beacon_address":"20:18:FF:00:40:08","system.totimestamp(timeuuid)":"2021-06-06T14:28:22.469Z","rssi":-74,"distance":1.202264434617412,"channel":38},{"beacon_address":"20:18:FF:00:40:08","system.totimestamp(timeuuid)":"2021-06-06T14:28:21.964Z","rssi":-65,"distance":0.9120108393559101,"channel":38},{"beacon_address":"20:18:FF:00:40:08","system.totimestamp(timeuuid)":"2021-06-06T14:28:21.456Z","rssi":-65,"distance":0.9120108393559101,"channel":38},{"beacon_address":"20:18:FF:00:40:08","system.totimestamp(timeuuid)":"2021-06-06T14:28:20.942Z","rssi":-74,"distance":0.9332543007969917,"channel":38},{"beacon_address":"20:18:FF:00:40:08","system.totimestamp(timeuuid)":"2021-06-06T14:28:20.426Z","rssi":-60,"distance":0.8912509381337456,"channel":37},{"beacon_address":"20:18:FF:00:40:08","system.totimestamp(timeuuid)":"2021-06-06T14:28:19.914Z","rssi":-62,"distance":1.3489628825916529,"channel":37},{"beacon_address":"20:18:FF:00:40:08","system.totimestamp(timeuuid)":"2021-06-06T14:28:19.403Z","rssi":-65,"distance":2.04173794466953,"channel":37},{"beacon_address":"20:18:FF:00:40:08","system.totimestamp(timeuuid)":"2021-06-06T14:28:18.891Z","rssi":-66,"distance":2.8183829312644537,"channel":37},{"beacon_address":"20:18:FF:00:40:08","system.totimestamp(timeuuid)":"2021-06-06T14:28:18.388Z","rssi":-72,"distance":3.715352290971728,"channel":37},{"beacon_address":"20:18:FF:00:40:08","system.totimestamp(timeuuid)":"2021-06-06T14:28:13.800Z","rssi":-78,"distance":4.2657951880159235,"channel":39}]