[{"system.totimestamp(timeuuid)":"2021-06-06T13:19:52.125Z","checkpoint":2},{"system.totimestamp(timeuuid)":"2021-06-06T13:20:01.859Z","checkpoint":7},{"system.totimestamp(timeuuid)":"2021-06-06T13:19:55.329Z","checkpoint":4},{"system.totimestamp(timeuuid)":"2021-06-06T13:19:49.886Z","checkpoint":1},{"system.totimestamp(timeuuid)":"2021-06-06T13:19:53.687Z","checkpoint":3},{"system.totimestamp(timeuuid)":"2021-06-06T13:19:59.368Z","checkpoint":6},{"system.totimestamp(timeuuid)":"2021-06-06T13:19:57.382Z","checkpoint":5},{"system.totimestamp(timeuuid)":"2021-06-06T13:20:04.076Z","checkpoint":8},{"system.totimestamp(timeuuid)":"2021-06-06T13:19:46.716Z","checkpoint":0}]